Workbook

Sheet Summary
A1: PERSONAL BUDGET — BRUSNAHAN HOUSEHOLD
A2: Source: Rocket Money export | Period analyzed: 2025-05-07 to 2026-05-06
A4: MONTHLY VIEW
A5: Average monthly income | B5: =Income!C2
A6: Fixed monthly costs | B6: =-'Fixed Costs'!D2
A7: Variable monthly spending | B7: =-'Variable Costs'!C2
A8: Surplus / (Deficit) per month | B8: =B5+B6+B7
A10: ANNUAL VIEW (last 12 months actual)
A11: Annual income | B11: =B5*12
A12: Annual fixed costs | B12: =B6*12
A13: Annual variable spending | B13: =B7*12
A14: Annual net | B14: =B11+B12+B13
A16: KEY RATIOS
A17: Fixed costs as % of income | B17: =-B6/B5
A18: Variable spend as % of income | B18: =-B7/B5
A19: Total expenses as % of income | B19: =(-B6-B7)/B5
A20: Savings rate (target ≥ 15%) | B20: =B8/B5
A22: FLAGS / OBSERVATIONS
A23: 1. Real deficit ≈ ($2,616)/mo, draining liquid savings. ~5 months runway on $15k MM+CD.
A24: 2. Already cracked Sabrina's 401k once at last low — pattern must not repeat.
A25: 3. Income locked at $8,236/mo (KSP COO contract + TG Admin + side biz).
A26: 4. Credit cards healthy (paid in full, no interest) — keep using Costco Visa for cashback.
A27: 5. See 'Action Plan' tab for ranked cuts (P1 = THIS WEEK, P2 = THIS MONTH, P3 = QUARTER).
A28: 6. See 'Weekly Tracker' tab — every Sunday review, 10 min. Non-negotiable.
A29: 7. See 'Path to Zero' tab to model alternative scenarios.

Sheet Action Plan
A1: ACTION PLAN — what has to change
A2: Income $8,236/mo. Burn rate ($2,616)/mo. Liquid runway ≈ 5 months. This is the gap-closing playbook.
A4: REALITY CHECK
A5: Monthly income | B5: 8236
A6: Monthly fixed costs | B6: -4545 | C6: Largely locked
A7: Monthly variable spend | B7: -6307 | C7: Where the gap lives
A8: Monthly surplus/(deficit) | B8: -2616 | C8: Eating into savings
A9: Liquid savings (MM + CD) | B9: 15000 | C9: $10k MM + $5k CD
A10: Months of runway at current burn | B10: 5.7 | C10: Real runway: ~4-5 months (don't break CD)
A12: CUTS NEEDED — ranked by impact
A13: Category | B13: Current $/mo | C13: Target $/mo | D13: Cut Required | E13: Cut % | F13: Priority | G13: How
A14: Shopping (Amazon, bulk stores) | B14: 1905 | C14: 700 | D14: =B14-C14 | E14: =(B14-C14)/B14 | F14: P1 — TODAY | G14: Delete saved cards from Amazon/Walmart/Target. Cap $162/wk. Force 24-hr wait on every cart.
A15: Dining & Drinks | B15: 809 | C15: 400 | D15: =B15-C15 | E15: =(B15-C15)/B15 | F15: P1 — TODAY | G15: Cap dining at 5% of income. $92/wk.
A16: Groceries | B16: 1183 | C16: 900 | D16: =B16-C16 | E16: =(B16-C16)/B16 | F16: P2 | G16: Meal-plan weekly. Costco strategy: buy bulk staples only, not impulse adds. $208/wk.
A17: Cash & Checks (Venmo/Zelle out) | B17: 403 | C17: 150 | D17: =B17-C17 | E17: =(B17-C17)/B17 | F17: P1 — IDENTIFY | G17: Tag every Zelle/Venmo destination. Some may be real bills mis-flowing. $35/wk hard cap.
A18: Entertainment & Recreation | B18: 251 | C18: 150 | D18: =B18-C18 | E18: =(B18-C18)/B18 | F18: P2 | G18: Free/cheap alternatives. Drop YouTube TV ($22).
A19: Travel & Vacation | B19: 234 | C19: 100 | D19: =B19-C19 | E19: =(B19-C19)/B19 | F19: P3 | G19: No new VRBO/trips for 90 days.
A20: Personal Care | B20: 106 | C20: 70 | D20: =B20-C20 | E20: =(B20-C20)/B20 | F20: P3 | G20: Stretch cycle 25%.
A21: Software & Tech | B21: 83 | C21: 55 | D21: =B21-C21 | E21: =(B21-C21)/B21 | F21: P3 | G21: Audit subscriptions.
A22: T-Mobile (fixed) | B22: 192 | C22: 100 | D22: =B22-C22 | E22: =(B22-C22)/B22 | F22: P2 | G22: Switch to prepaid carrier (US Mobile/Mint/Visible).
A23: Progressive Auto (fixed) | B23: 216 | C23: 185 | D23: =B23-C23 | E23: =(B23-C23)/B23 | F23: P2 | G23: Get one quote from Geico/State Farm.
A24: Cox Internet (fixed) | B24: 100 | C24: 85 | D24: =B24-C24 | E24: =(B24-C24)/B24 | F24: P3 | G24: Negotiate or switch to lower tier.
A25: Pest Control (fixed) | B25: 44 | C25: 22 | D25: =B25-C25 | E25: =(B25-C25)/B25 | F25: P3 | G25: Quarterly instead of monthly.
A26: Subscriptions trim (Netflix/Apple) | B26: 63 | C26: 40 | D26: =B26-C26 | E26: =(B26-C26)/B26 | F26: P3 | G26: Drop one streaming, consolidate Apple.
A27: TOTAL MONTHLY SAVINGS IF ALL HIT | D27: =SUM(D14:D26)
A29: INCOME SIDE — every dollar counts
A31: Grow side businesses 25% (Photo + Nails) | B31: 286 | C31: Most accessible income lever you have
A32: Sell unused photography gear / household items | B32: 100 | C32: One-time, not monthly — but adds to runway
A33: Look for billable freelance hours | B33: 200 | C33: If photography skills support occasional paid gigs
A36: PROJECTED MONTHLY SURPLUS IF P1+P2 HIT + INCOME GROWS 25% | B36: ≈ +$200 to +$500/mo

Sheet Weekly Tracker
A1: WEEKLY CHECK-IN — every Sunday, 10 minutes
A2: Enter your spending each week per category. Cells turn RED if over weekly cap, GREEN if under. Keep month-to-date in mind.
A4: Category | B4: Monthly Cap | C4: Weekly Cap | D4: Week 1 | E4: Week 2 | F4: Week 3 | G4: Week 4 | H4: Month-to-Date | I4: Remaining
A5: Shopping | B5: 700 | C5: =B5/4.33 | D5: 0 | E5: 0 | F5: 0 | G5: 0 | H5: =SUM(D5:G5) | I5: =B5-H5
A6: Dining & Drinks | B6: 400 | C6: =B6/4.33 | D6: 0 | E6: 0 | F6: 0 | G6: 0 | H6: =SUM(D6:G6) | I6: =B6-H6
A7: Groceries | B7: 900 | C7: =B7/4.33 | D7: 0 | E7: 0 | F7: 0 | G7: 0 | H7: =SUM(D7:G7) | I7: =B7-H7
A8: Cash/Venmo/Zelle out | B8: 150 | C8: =B8/4.33 | D8: 0 | E8: 0 | F8: 0 | G8: 0 | H8: =SUM(D8:G8) | I8: =B8-H8
A9: Auto & Transport | B9: 325 | C9: =B9/4.33 | D9: 0 | E9: 0 | F9: 0 | G9: 0 | H9: =SUM(D9:G9) | I9: =B9-H9
A10: Entertainment | B10: 150 | C10: =B10/4.33 | D10: 0 | E10: 0 | F10: 0 | G10: 0 | H10: =SUM(D10:G10) | I10: =B10-H10
A11: Personal Care | B11: 70 | C11: =B11/4.33 | D11: 0 | E11: 0 | F11: 0 | G11: 0 | H11: =SUM(D11:G11) | I11: =B11-H11
A12: Software & Tech | B12: 55 | C12: =B12/4.33 | D12: 0 | E12: 0 | F12: 0 | G12: 0 | H12: =SUM(D12:G12) | I12: =B12-H12
A13: TOTAL | B13: =SUM(B5:B12) | C13: =SUM(C5:C12) | D13: =SUM(D5:D12) | E13: =SUM(E5:E12) | F13: =SUM(F5:F12) | G13: =SUM(G5:G12) | H13: =SUM(H5:H12) | I13: =SUM(I5:I12)
A16: SUNDAY 10-MINUTE REVIEW CHECKLIST
A17: 1. Open Rocket Money. Filter to last 7 days. Tally each category.
A18: 2. Enter each weekly total in the appropriate Week column above. Cells turn red if you blew the weekly cap.
A19: 3. If any category is RED — discuss with Sabrina what triggered the overrun.
A20: 4. If 'Remaining' is negative on any category 3+ weeks in a row — the cap is wrong or the habit isn't sticking. Recalibrate.
A21: 5. Check the runway: liquid savings should be growing each week if you're hitting targets. If not, there's a leak you haven't caught yet.
A22: 6. At month-end, compare TOTAL row to overall monthly cap of $2,750. Reset all weekly cells for the new month.
A23: 7. This habit is the difference between 'we tried' and 'we actually did it'. Don't skip Sundays.

Sheet Income
A1: Source | B1: Annual ($) | C1: Monthly Avg | D1: # Txns | E1: Notes
A2: TOTAL | B2: =SUM(B4:B12) | C2: =B2/12 | D2: =SUM(D4:D12)
A4: Kingdom Structural Payroll | B4: 39620.5 | C4: =B4/12 | D4: 40 | E4: Primary salary
A5: TG Admin LLC Payroll | B5: 36882.94 | C5: =B5/12 | D5: 15 | E5: Secondary employer payroll
A6: Side businesses (Photography + Nails) | B6: 13742.34 | C6: =B6/12 | D6: 56 | E6: Sabrina's nails + Michael's photography — Venmo deposits
A7: Other income | B7: 2468.06 | C7: =B7/12 | D7: 44 | E7: Misc — verify which are real income
A8: Inter-account transfers (income side) | B8: 2233 | C8: =B8/12 | D8: 5 | E8: Transfers from other accounts — likely NOT income
A9: Tax refunds | B9: 1991.6 | C9: =B9/12 | D9: 1 | E9: One-time / annual
A10: Amazon refunds | B10: 1743.81 | C10: =B10/12 | D10: 60 | E10: Returns — not real income
A11: Cash deposits | B11: 139.8 | C11: =B11/12 | D11: 11 | E11: ATM deposits
A12: Interest / Dividends | B12: 14.84 | C12: =B12/12 | D12: 14 | E12: Bank interest

Sheet Fixed Costs
A1: Group | B1: Item | C1: Annual ($) | D1: Monthly Avg | E1: Months Seen | F1: # Txns | G1: Notes
A2: TOTAL | C2: =SUM(C4:C18) | D2: =C2/12 | F2: =SUM(F4:F18)
A4: Debt / Loans | B4: Auto loan (JPMorgan Chase) | C4: 5932.96 | D4: =C4/12 | E4: 11 | F4: 11 | G4: Auto loan — financed vehicle, confirmed recurring
A5: Home Services | B5: Pest Control | C5: 523 | D5: =C5/12 | E5: 7 | F5: 7 | G5: Quarterly? Verify recurrence
A6: Housing | B6: Rent | C6: 33240 | D6: =C6/12 | E6: 12 | F6: 9 | G6: $2,770/mo confirmed × 12. Export only showed 9 months — annualized to true cost.
A7: Insurance | B7: Progressive Auto | C7: 2594.46 | D7: =C7/12 | E7: 12 | F7: 12
A8: Medical | B8: Affinity Medical | C8: 1285 | D8: =C8/12 | E8: 7 | F8: 9 | G8: Medical — confirmed (was 'Affinity (?)')
A9: Subscriptions | B9: Pass Gallery (photo editing) | C9: 550.17 | D9: =C9/12 | E9: 12 | F9: 13 | G9: Photo editing software — supports photography side income
A10: Subscriptions | B10: Netflix | C10: 441.6 | D10: =C10/12 | E10: 12 | F10: 12
A11: Subscriptions | B11: Apple services | C11: 312.66 | D11: =C11/12 | E11: 12 | F11: 35 | G11: Multiple Apple subscriptions — review
A12: Subscriptions | B12: Amazon Prime | C12: 301.68 | D12: =C12/12 | E12: 10 | F12: 19
A13: Subscriptions | B13: Spotify | C13: 266.31 | D13: =C13/12 | E13: 12 | F13: 12
A14: Utilities | B14: SRP Electric | C14: 2967.9 | D14: =C14/12 | E14: 12 | F14: 12
A15: Utilities | B15: T-Mobile (cell) | C15: 2301.6 | D15: =C15/12 | E15: 12 | F15: 12
A16: Utilities | B16: Gilbert Water | C16: 2207.49 | D16: =C16/12 | E16: 10 | F16: 10
A17: Utilities | B17: Cox Internet | C17: 1200 | D17: =C17/12 | E17: 12 | F17: 12
A18: Utilities | B18: Southwest Gas | C18: 420 | D18: =C18/12 | E18: 12 | F18: 12 | G18: Recurring gas bill — was hiding in Variable B&U

Sheet Variable Costs
A1: Category | B1: Annual Spent ($) | C1: Monthly Avg | D1: Suggested Target ($/mo) | E1: Variance vs Target | F1: Notes
A2: TOTAL | B2: =SUM(B4:B23) | C2: =SUM(C4:C23) | D2: =SUM(D4:D23) | E2: =C2-D2
A4: Shopping | B4: 22864.81 | C4: =B4/12 | D4: 1334 | E4: =C4-D4
A5: Groceries | B5: 14192.03 | C5: =B5/12 | D5: 1124 | E5: =C5-D5
A6: Dining & Drinks | B6: 9704.76 | C6: =B6/12 | D6: 526 | E6: =C6-D6
A7: Bills & Utilities | B7: 565.63 | C7: =B7/12 | D7: 47 | E7: =C7-D7 | F7: CORRECTED — was contaminated with rent payments. True B&U is ~$47/mo (Southwest Gas now moved to Fixed)
A8: Savings Transfer | B8: 5250 | C8: =B8/12 | D8: 416 | E8: =C8-D8 | F8: Self-transfers to savings — keep targeted but track separately
A9: Cash & Checks | B9: 4834.94 | C9: =B9/12 | D9: 383 | E9: =C9-D9 | F9: Cash withdrawals — destination unknown, watch closely
A10: Auto & Transport | B10: 4301.82 | C10: =B10/12 | D10: 341 | E10: =C10-D10
A11: Entertainment & Rec. | B11: 3011.31 | C11: =B11/12 | D11: 188 | E11: =C11-D11
A12: Travel & Vacation | B12: 2810.76 | C12: =B12/12 | D12: 187 | E12: =C12-D12
A13: Uncategorized | B13: 2579.06 | C13: =B13/12 | D13: 107 | E13: =C13-D13 | F13: Categorize these in Rocket Money for clearer picture
A14: Loan Payment | B14: 0 | C14: =B14/12 | D14: 0 | E14: =C14-D14 | F14: RESOLVED — internal DFCU transfer, not a real loan payment
A15: Medical | B15: 1393.2 | C15: =B15/12 | D15: 110 | E15: =C15-D15
A16: Personal Care | B16: 1267.4 | C16: =B16/12 | D16: 90 | E16: =C16-D16
A17: Health & Wellness | B17: 1027.46 | C17: =B17/12 | D17: 81 | E17: =C17-D17
A18: Software & Tech | B18: 997.47 | C18: =B18/12 | D18: 66 | E18: =C18-D18
A19: Pets | B19: 586.13 | C19: =B19/12 | D19: 46 | E19: =C19-D19
A20: Fees | B20: 462.36 | C20: =B20/12 | D20: 37 | E20: =C20-D20
A21: Home & Garden | B21: 185.94 | C21: =B21/12 | D21: 15 | E21: =C21-D21
A22: Charitable Donations | B22: 183.09 | C22: =B22/12 | D22: 14 | E22: =C22-D22
A23: Education | B23: 31.75 | C23: =B23/12 | D23: 3 | E23: =C23-D23

Sheet Top Vendors
A1: TOP VENDORS — last 12 months variable spend
A2: Excludes Fixed Costs already on its own tab. Excludes internal transfers/CC payments.
A4: OVERALL — Top 30
A5: Rank | B5: Merchant | C5: 12-mo Total | D5: Monthly Avg | E5: Txns | F5: Months Active
A6: 1 | B6: FRY'S FOOD | C6: 14550.18 | D6: =C6/12 | E6: 144 | F6: 13
A7: 2 | B7: AMAZON | C7: 11140.5 | D7: =C7/12 | E7: 285 | F7: 12
A8: 4 | B8: VRBO HAN7VXGM | C8: 2704.01 | D8: =C8/12 | E8: 1 | F8: 1
A9: 5 | B9: WALMART | C9: 2126.39 | D9: =C9/12 | E9: 19 | F9: 9
A10: 6 | B10: TARGET | C10: 1946.07 | D10: =C10/12 | E10: 32 | F10: 10
A11: 7 | B11: SAM'S CLUB | C11: 1938.41 | D11: =C11/12 | E11: 12 | F11: 7
A12: 8 | B12: VENMO PAYMENT OUT | C12: 1274.24 | D12: =C12/12 | E12: 17 | F12: 8
A13: 9 | B13: CASH WITHDRAWAL | C13: 1200 | D13: =C13/12 | E13: 1 | F13: 1
A14: 10 | B14: SAMSCLUB.COM | C14: 1089.28 | D14: =C14/12 | E14: 7 | F14: 4
A15: 11 | B15: PAYPAL | C15: 1043.22 | D15: =C15/12 | E15: 20 | F15: 10
A16: 13 | B16: NUVISION AUTO GLASS LLC | C16: 990.4 | D16: =C16/12 | E16: 2 | F16: 1
A17: 14 | B17: DESERT FINANCIAL CREDIT UNION | C17: 880 | D17: =C17/12 | E17: 3 | F17: 2
... A29: 30 | B29: BHC GILBERT | C29: 413 | D29: =C29/12 | E29: 1 | F29: 1
A32: SHOPPING — Top 12
A33: Rank | B33: Merchant | C33: 12-mo Total | D33: Monthly Avg | E33: Txns | F33: Months Active
A34: 1 | B34: AMAZON | C34: 10722.84 | D34: =C34/12 | E34: 251 | F34: 12
A35: 2 | B35: WALMART | C35: 2126.39 | D35: =C35/12 | E35: 19 | F35: 9
A36: 3 | B36: TARGET | C36: 1946.07 | D36: =C36/12 | E36: 32 | F36: 10
A37: 4 | B37: SAM'S CLUB | C37: 1938.41 | D37: =C37/12 | E37: 12 | F37: 7
A38: 5 | B38: SAMSCLUB.COM | C38: 1089.28 | D38: =C38/12 | E38: 7 | F38: 4
A39: 6 | B39: COSTCO | C39: 614.55 | D39: =C39/12 | E39: 6 | F39: 4
A40: 7 | B40: SHEIN.COM | C40: 445.19 | D40: =C40/12 | E40: 2 | F40: 2
A41: 8 | B41: CIRCLE K | C41: 377.86 | D41: =C41/12 | E41: 11 | F41: 6
A42: 9 | B42: NELLIS AUCTION | C42: 363.69 | D42: =C42/12 | E42: 4 | F42: 3
A43: 10 | B43: SAMSCLUB.COM AR 62790089 | C43: 354.3 | D43: =C43/12 | E43: 3 | F43: 3
A44: 11 | B44: AZAZIE INC | C44: 278.58 | D44: =C44/12 | E44: 1 | F44: 1
A45: 12 | B45: OLD NAVY | C45: 237.6 | D45: =C45/12 | E45: 1 | F45: 1
A47: DINING & DRINKS — Top 12
A48: Rank | B48: Merchant | C48: 12-mo Total | D48: Monthly Avg | E48: Txns | F48: Months Active
A49: 1 | B49: FRY'S FOOD | C49: 1882.79 | D49: =C49/12 | E49: 16 | F49: 3
A50: 2 | B50: MCDONALD'S | C50: 422.7 | D50: =C50/12 | E50: 20 | F50: 11
A51: 3 | B51: DUNKIN' | C51: 327.06 | D51: =C51/12 | E51: 27 | F51: 12
A52: 4 | B52: TST*PICAZZOS HEALTHY IT | C52: 286.98 | D52: =C52/12 | E52: 1 | F52: 1
A53: 5 | B53: CHICK-FIL-A | C53: 273.83 | D53: =C53/12 | E53: 7 | F53: 6
A54: 6 | B54: DOMINO'S | C54: 242.8 | D54: =C54/12 | E54: 7 | F54: 5
A55: 7 | B55: CHIPOTLE MEXICAN GRILL | C55: 197 | D55: =C55/12 | E55: 9 | F55: 7
A56: 8 | B56: TACO BELL | C56: 182.2 | D56: =C56/12 | E56: 13 | F56: 8
A57: 9 | B57: TST* POSTINO - EAST | C57: 179.19 | D57: =C57/12 | E57: 4 | F57: 4
A58: 10 | B58: TST*CALL HER MARTINA | C58: 161.28 | D58: =C58/12 | E58: 1 | F58: 1
A59: 11 | B59: UBER * EATS PE SAN FRANCISCO CA 00000000 | C59: 158.62 | D59: =C59/12 | E59: 2 | F59: 2
A60: 12 | B60: TST*NEW - THE WHINING PI | C60: 146.24 | D60: =C60/12 | E60: 2 | F60: 2
A62: GROCERIES — Top 12
A63: Rank | B63: Merchant | C63: 12-mo Total | D63: Monthly Avg | E63: Txns | F63: Months Active
A64: 1 | B64: FRY'S FOOD | C64: 12216.9 | D64: =C64/12 | E64: 118 | F64: 13
A65: 2 | B65: THRIVE MARKET CA 00000000 | C65: 672.93 | D65: =C65/12 | E65: 7 | F65: 6
A66: 3 | B66: TRADER JOE'S | C66: 382.68 | D66: =C66/12 | E66: 7 | F66: 6
A67: 4 | B67: THRIVE MARKET | C67: 331.24 | D67: =C67/12 | E67: 5 | F67: 5
A68: 5 | B68: COOPER'S HAWK GILBE GILBERT AZ 00002997 | C68: 179.57 | D68: =C68/12 | E68: 1 | F68: 1
A69: 6 | B69: ALDI | C69: 101.01 | D69: =C69/12 | E69: 1 | F69: 1
A70: 7 | B70: SAFEWAY | C70: 100.88 | D70: =C70/12 | E70: 3 | F70: 2
A71: 8 | B71: THRIVE MARKET CA ****0000 | C71: 83.01 | D71: =C71/12 | E71: 1 | F71: 1
A72: 9 | B72: PHTOSHP LIGHTRM SAN JOSE CA XX0000 | C72: 48.69 | D72: =C72/12 | E72: 3 | F72: 3
A73: 10 | B73: K-VA-T FOOD CITY | C73: 20.32 | D73: =C73/12 | E73: 1 | F73: 1
A74: 11 | B74: ALBERTSONS | C74: 19.85 | D74: =C74/12 | E74: 2 | F74: 2
A75: 12 | B75: CHEFSTORE 8105 | C75: 18.72 | D75: =C75/12 | E75: 1 | F75: 1
A77: AUTO & TRANSPORT — Top 12
A78: Rank | B78: Merchant | C78: 12-mo Total | D78: Monthly Avg | E78: Txns | F78: Months Active
A79: 1 | B79: NUVISION AUTO GLASS LLC | C79: 990.4 | D79: =C79/12 | E79: 2 | F79: 1
A80: 2 | B80: DISCOUNT-TIRE-CO-AZP | C80: 499.34 | D80: =C80/12 | E80: 1 | F80: 1
A81: 3 | B81: FRY'S FOOD | C81: 450.49 | D81: =C81/12 | E81: 10 | F81: 7
A82: 4 | B82: QUIKTRIP | C82: 292.91 | D82: =C82/12 | E82: 6 | F82: 5
A83: 5 | B83: CHEVRON | C83: 292.45 | D83: =C83/12 | E83: 6 | F83: 5
A84: 6 | B84: AZ MVD FEE | C84: 254.04 | D84: =C84/12 | E84: 3 | F84: 1
A85: 7 | B85: CIRCLE K | C85: 244.14 | D85: =C85/12 | E85: 9 | F85: 4
A86: 8 | B86: NORTH TEXAS TOLLWAY AUTHORITY | C86: 177.02 | D86: =C86/12 | E86: 2 | F86: 1
A87: 9 | B87: AUTOZONE | C87: 170.24 | D87: =C87/12 | E87: 4 | F87: 4
A88: 10 | B88: B&B TOWING MESA AZ 09/04 | C88: 120 | D88: =C88/12 | E88: 1 | F88: 1
A89: 11 | B89: EOC03007 | C89: 110.48 | D89: =C89/12 | E89: 1 | F89: 1
A90: 12 | B90: SHELL | C90: 64.58 | D90: =C90/12 | E90: 2 | F90: 2
A92: ENTERTAINMENT & REC. — Top 12
A93: Rank | B93: Merchant | C93: 12-mo Total | D93: Monthly Avg | E93: Txns | F93: Months Active
A94: 1 | B94: GAMESHOWBATTLEROOMS | C94: 459.88 | D94: =C94/12 | E94: 2 | F94: 2
A95: 2 | B95: PHOENIX ZOO AZ 05/25 | C95: 289 | D95: =C95/12 | E95: 1 | F95: 1
A96: 3 | B96: GOOGLE YOUTUBE TV | C96: 268.41 | D96: =C96/12 | E96: 3 | F96: 3
A97: 4 | B97: AMAZON | C97: 263.96 | D97: =C97/12 | E97: 31 | F97: 12
A98: 5 | B98: I D E A MUSEUM RETAIL | C98: 200 | D98: =C98/12 | E98: 2 | F98: 2
A99: 6 | B99: GLF*WESTERNSKIESGOLF | C99: 141.88 | D99: =C99/12 | E99: 3 | F99: 2
A100: 7 | B100: SILVERADO GOLF COURSE | C100: 130.52 | D100: =C100/12 | E100: 1 | F100: 1
A101: 8 | B101: APPLE | C101: 127.74 | D101: =C101/12 | E101: 8 | F101: 5
A102: 9 | B102: POPSTROKE 156-12037974 FL YTIGKNGH | C102: 108.24 | D102: =C102/12 | E102: 1 | F102: 1
A103: 10 | B103: TOPGOLF GILBERT 014-2 | C103: 107.47 | D103: =C103/12 | E103: 1 | F103: 1
A104: 11 | B104: 4UP*PAINTED MTN GC | C104: 86.64 | D104: =C104/12 | E104: 1 | F104: 1
A105: 12 | B105: PLAYSTATION NETWORK | C105: 86.58 | D105: =C105/12 | E105: 4 | F105: 4
A107: BILLS & UTILITIES — Top 12
A108: Rank | B108: Merchant | C108: 12-mo Total | D108: Monthly Avg | E108: Txns | F108: Months Active
A109: 1 | B109: SOUTHWEST GAS BILLPAY SABRINABRUSNAHAN | C109: 315.92 | D109: =C109/12 | E109: 9 | F109: 8
A110: 2 | B110: PAYMENT TO SOUTHWEST GAS | C110: 104.46 | D110: =C110/12 | E110: 3 | F110: 3
A111: 3 | B111: FRONTIER SEC WEB | C111: 58.49 | D111: =C111/12 | E111: 1 | F111: 1
A112: 4 | B112: VARSITY ENERGY LLC | C112: 25.87 | D112: =C112/12 | E112: 1 | F112: 1
A113: 5 | B113: USPS PO 225 S GILBERT AZ 12/18 | C113: 21.95 | D113: =C113/12 | E113: 1 | F113: 1
A114: 6 | B114: USPS PO 225 S GILBERT AZ 08/28 | C114: 15.95 | D114: =C114/12 | E114: 1 | F114: 1
A115: 7 | B115: ACT*GILBERTPARKSREC | C115: 12 | D115: =C115/12 | E115: 2 | F115: 1
A116: 8 | B116: UBER *ONE MEMBERSHIP | C116: 9.99 | D116: =C116/12 | E116: 1 | F116: 1
A117: 9 | B117: CITY OF FLAGSTAFF FLAG | C117: 1 | D117: =C117/12 | E117: 1 | F117: 1
A119: CASH & CHECKS — Top 12
A120: Rank | B120: Merchant | C120: 12-mo Total | D120: Monthly Avg | E120: Txns | F120: Months Active
...

Sheet Path to Zero
A1: PATH TO +$500/MO — interactive scenario
A2: Edit BLUE cells (% kept of current spend, side-biz growth %). Surplus updates live. Goal: +$500/mo.
A4: INCOME
A5: Source | B5: Current $/mo | C5: Growth % | D5: New $/mo | F5: Notes
A6: Kingdom Structural Payroll (locked — COO contract) | B6: 3301.71 | C6: 0 | D6: =B6*(1+C6) | F6: Contract — no change available
A7: TG Admin LLC Payroll | B7: 3073.58 | C7: 0 | D7: =B7*(1+C7) | F7: Steady employer pay
A8: Side businesses (Photo + Nails) | B8: 1145.2 | C8: 0.25 | D8: =B8*(1+C8) | F8: Editable: % growth assumed
A9: Other (interest, refunds, transfers) | B9: 716 | C9: 0 | D9: =B9*(1+C9) | F9: Misc — assume flat
A10: TOTAL INCOME | B10: =SUM(B6:B9) | D10: =SUM(D6:D9)
A12: FIXED COSTS
A13: Item | B13: Current $/mo | C13: Cut % | D13: New $/mo | F13: Notes
A14: Rent | B14: 2770 | C14: 0 | D14: =B14*(1-C14) | F14: Locked until lease renewal
A15: Auto loan (JPMorgan) | B15: 494.41 | C15: 0 | D15: =B15*(1-C15) | F15: Locked
A16: SRP Electric | B16: 247.33 | C16: 0 | D16: =B16*(1-C16) | F16: Mostly fixed; minor savings via thermostat
A17: Progressive Auto | B17: 216.21 | C17: 0.1 | D17: =B17*(1-C17) | F17: Editable — shop quotes for 10% cut
A18: T-Mobile | B18: 191.8 | C18: 0.4 | D18: =B18*(1-C18) | F18: Editable — switch to prepaid for big cut
A19: Gilbert Water | B19: 183.96 | C19: 0 | D19: =B19*(1-C19) | F19: Locked
A20: Affinity Medical | B20: 107.08 | C20: 0 | D20: =B20*(1-C20) | F20: Necessary
A21: Cox Internet | B21: 100 | C21: 0.1 | D21: =B21*(1-C21) | F21: Editable — shop alternatives
A22: Pass Gallery (photo software) | B22: 45.85 | C22: 0 | D22: =B22*(1-C22) | F22: Business expense for photo income
A23: Pest Control | B23: 43.58 | C23: 0.5 | D23: =B23*(1-C23) | F23: Editable — DIY or quarterly
A24: Netflix | B24: 36.8 | C24: 0 | D24: =B24*(1-C24) | F24: Editable
A25: Southwest Gas | B25: 35 | C25: 0 | D25: =B25*(1-C25) | F25: Newly identified — locked
... A28: Spotify | B28: 22.19 | C28: 0 | D28: =B28*(1-C28) | F28: Keep
A29: TOTAL FIXED | B29: =SUM(B14:B28) | D29: =SUM(D14:D28)
A31: VARIABLE SPENDING
A32: Item | B32: Current $/mo | C32: Cut % | D32: New $/mo | F32: Notes
A33: Shopping (Amazon, Walmart, Target, Sam's, etc.) | B33: 1905.4 | C33: 0.6 | D33: =B33*(1-C33) | F33: BIGGEST LEVER — Amazon $928/mo, lots of impulse
A34: Groceries (mostly Fry's $1,212/mo) | B34: 1182.67 | C34: 0.25 | D34: =B34*(1-C34) | F34: Aggressive but realistic
A35: Dining & Drinks | B35: 808.73 | C35: 0.5 | D35: =B35*(1-C35) | F35: Target ≤5% of income = $412
A36: Cash & Checks (Venmo/Zelle/PayPal out) | B36: 402.91 | C36: 0.6 | D36: =B36*(1-C36) | F36: Untracked drift — biggest mystery
A37: Auto & Transport (gas + repairs) | B37: 358.49 | C37: 0.1 | D37: =B37*(1-C37) | F37: Mostly gas — limited room
A38: Entertainment & Recreation | B38: 250.94 | C38: 0.4 | D38: =B38*(1-C38) | F38: Outings + YouTube TV $22
A39: Travel & Vacation | B39: 234.23 | C39: 0.5 | D39: =B39*(1-C39) | F39: Inflated by VRBO one-off
A40: Uncategorized | B40: 214.92 | C40: 0.5 | D40: =B40*(1-C40) | F40: Categorize in RM for clarity
A41: Loan Payment (Desert Financial) | B41: 0 | C41: 0 | D41: =B41*(1-C41) | F41: RESOLVED — likely internal DFCU transfer, not a loan. Confirmed no open loans.
A42: Personal Care | B42: 105.62 | C42: 0.3 | D42: =B42*(1-C42)
A43: Health & Wellness | B43: 85.62 | C43: 0.2 | D43: =B43*(1-C43)
A44: Software & Tech | B44: 83.12 | C44: 0.3 | D44: =B44*(1-C44)
A45: Medical (out-of-pocket) | B45: 116.1 | C45: 0 | D45: =B45*(1-C45) | F45: Necessary
A46: Savings Transfer | B46: 437.5 | C46: 0 | D46: =B46*(1-C46) | F46: Already going to savings — keep
A47: Pets | B47: 48.84 | C47: 0 | D47: =B47*(1-C47)
A48: Fees | B48: 38.53 | C48: 0.5 | D48: =B48*(1-C48) | F48: Avoidable bank/late fees
A49: Home & Garden | B49: 15.5 | C49: 0 | D49: =B49*(1-C49)
A50: Charitable Donations | B50: 15.26 | C50: 0 | D50: =B50*(1-C50) | F50: Personal value — keep
A51: Education | B51: 2.65 | C51: 0 | D51: =B51*(1-C51)
A52: TOTAL VARIABLE | B52: =SUM(B33:B51) | D52: =SUM(D33:D51)
A54: RESULT
A55: Metric | B55: Today | D55: Scenario
A56: Total income | B56: =B10 | D56: =D10
A57: Total expenses (fixed + variable) | B57: =B29+B52 | D57: =D29+D52
A58: MONTHLY SURPLUS / (DEFICIT) | B58: =B56-B57 | D58: =D56-D57
A59: Annual surplus / (deficit) | B59: =B58*12 | D59: =D58*12
A60: Distance from +$500/mo goal | D60: =D58-500

Sheet Targets
A1: BUDGET PLAN — closing the deficit
A3: Item | B3: Current ($/mo) | C3: Target ($/mo) | D3: Monthly Save | E3: Annual Save
A4: Income | B4: =Income!C2 | C4: =B4 | D4: =C4-B4 | E4: =D4*12
A5: Fixed costs | B5: =-'Fixed Costs'!D2 | C5: =B5 | D5: =C5-B5 | E5: =D5*12
A6: Variable spending (current run rate) | B6: =-'Variable Costs'!C2 | C6: =-'Variable Costs'!D2 | D6: =C6-B6 | E6: =D6*12
A7: Net per month | B7: =B4+B5+B6 | C7: =C4+C5+C6 | D7: =D4+D5+D6 | E7: =D7*12
A9: ACTION ITEMS
A10: Cancel unknown subscriptions ('Affinity', 'Pass Gallery') if not needed | B10: ≈$153/mo savings
A11: Audit 'Bills & Utilities' Variable bucket — move recurring bills into Fixed list | B11: Better visibility
A12: Cut Shopping by 30% | B12: ≈$571/mo savings
A13: Cut Dining & Drinks by 35% | B13: ≈$283/mo savings
A14: Cut Entertainment by 25% | B14: ≈$63/mo savings
A15: Tag Venmo income — only count true personal income | B15: Better deficit picture
A16: Categorize 'Uncategorized' rows in Rocket Money | B16: Visibility
A17: Verify Rent shows 9 months — start month? | B17: Validates fixed cost
A18: Verify JPMorgan transfer purpose ($494/mo) | B18: May or may not be a real bill

Sheet Methodology
A1: How this budget was built
A3: Source file | B3: rocket_money_export.csv.csv (Rocket Money)
A4: Period | B4: 2025-05-07 to 2026-05-06 (last 12 months)
A5: Sign convention | B5: Negative amounts = money in, positive = money out
A6: Excluded | B6: Rows where 'Ignored From' is set, plus Categories: Internal Transfers, Credit Card Payment (those are moves between own accounts, not real income/expenses)
A7: Income consolidation | B7: Rows with Amount<0 grouped by merchant keywords: KINGDOM, TG ADMIN, Venmo, Amazon refunds, Interest, Tax refunds, etc.
A8: Fixed cost classification | B8: Hand-curated keyword list (Occasio, Cox, T-Mobile, SRP, Town of Gilbert, Progressive, Netflix, Spotify, Amazon Prime, Apple, JPMorgan transfer, Pest Control)
A9: Variable cost classification | B9: Everything not classified as Fixed, grouped by Rocket Money's Category column
A10: Targets | B10: Rough first cut: Shopping -30%, Dining -35%, Entertainment -25%, Uncategorized -50%, others -5 to -20%
A11: Things to verify | B11: Rent shows 9 of 12 months — confirm start date. Venmo income — likely reimbursements not real pay. Two unknown subscriptions. JPMorgan Chase transfer destination.
A12: How to refresh | B12: Re-export Rocket Money CSV to _automation/, re-run the analysis script. The Excel inputs (blue text) can be overridden in place if you disagree with a classification.
